testbench/des.v


module des(
    input clock,
    input enable,
    input load,
    input din,
    output [31:0]dout
);
wire [4:0]count;
wire [31:0]reg_data;
wire des_d_in;
wire rst;

tribuf TRIBUF(din,enable,des_d_in);
d_demux16x4 DEMUX16X4(des_d_in,count,reg_data);
d_cnt4bit SEL_DEMUX(clock,load,count);
d_data DATA(reg_data,load,clock,dout);



endmodule



module d_data(
	input [31:0]din,
	input load,
	input clk,
	output reg [31:0]temp
);

always @(posedge clk) begin
	if(load) begin
		temp<=din;
	end

	else begin
		temp<=temp;
    end
end

endmodule


module d_cnt4bit(
input clock,
input load,
output reg [4:0]count
);

always @ (posedge clock) begin
    if (!load)
        count<=count+5'd1;
    else
        count<=5'd0;
end

endmodule

module d_demux16x4 (
	input d_in,
	input [4:0]sel,
	output reg [31:0]d_out
);

always @(*) begin
	d_out[sel]<=d_in;
end
endmodule

module tribuf(
    input d_in,
    input enable,
    output d_out
);

assign d_out=enable?d_in:1'bz;
endmodule

testbench/ser.v
//RTL Code of serializer 

module ser(
    input clock,
    input enable,
    input load,
    input [31:0]din,
    output dout
);


wire [4:0]count;
wire [31:0]reg_data;
wire d_out;
wire rst;

cnt4bit SEL_MUX(clock,load,count);
data DATA(din,load,clock,rst,reg_data);
mux16x4 MUX16X4(reg_data,count,enable,d_out);
s_tribuf TRIBUFF(enable,d_out,dout);


endmodule



module data(
	input [31:0]din,
	input load,
	input clk,
    output reg rst,
	output reg [31:0]temp
);


always @(posedge clk) begin
	if(load) begin
		temp<=din;
        rst<=1'b0;
	end
	else begin
		temp<=temp;
        rst<=1'b1;
    end
end

endmodule


module cnt4bit(
input clock,
input load,
output reg [4:0]count
);

always @ (posedge clock) begin
    if (!load)
        count<=count+5'd1;
    else
        count<=5'd0;
end

endmodule

module mux16x4 (
	input [31:0]d_in,
	input [4:0]sel,
        input enable,
	output reg d_out
);

always @(*) begin
	d_out<=d_in[sel];
end

endmodule

module s_tribuf(input enable, input din, output reg dout);
always @ (*)
begin
if(enable) dout<=din;
else dout<=1'bz; //for gds, 0
end
endmodule

testbench/tb.v
`include "ser.v"
`include "des.v"
`timescale 1ns/1ps
module main;

reg clock;
reg enable;
reg [31:0]din;
reg load;
wire dout;
reg d_out;
wire [31:0]rx_data;

ser s1(.clock(clock),.enable(enable),.din(din),.dout(dout),.load(load));
des d1(.clock(clock),.enable(enable),.din(dout),.dout(rx_data),.load(load));

initial begin
    clock=0;
    enable=0;

    forever begin
        #5 clock=~clock;
    end
end

initial begin

    din=32'h12345678;
    #20;
    forever begin
        #320 din=$random;
    end


end

initial begin
    #19 enable=1;
    load=1;
    #10 load=0;

    #4000 $finish;
end


initial
begin
    load=0;
    #20 load=1;
    #10 load=0;
    forever begin
        #310 load=~load;
        #10 load=~load;
    end
end
initial begin
    $dumpfile("dump.vcd");
    $dumpvars(0,main);
end


endmodule

testbench/dump.vcd
$date
	Sat Aug 12 22:09:12 2023
$end
$version
	Icarus Verilog
$end
$timescale
	1ps
$end
$scope module main $end
$var wire 32 ! rx_data [31:0] $end
$var wire 1 " dout $end
$var reg 1 # clock $end
$var reg 32 $ din [31:0] $end
$var reg 1 % enable $end
$var reg 1 & load $end
$scope module d1 $end
$var wire 1 # clock $end
$var wire 1 % enable $end
$var wire 1 & load $end
$var wire 32 ' reg_data [31:0] $end
$var wire 32 ( dout [31:0] $end
$var wire 1 " din $end
$var wire 1 ) des_d_in $end
$var wire 5 * count [4:0] $end
$scope module DATA $end
$var wire 1 # clk $end
$var wire 1 & load $end
$var wire 32 + din [31:0] $end
$var reg 32 , temp [31:0] $end
$upscope $end
$scope module DEMUX16X4 $end
$var wire 5 - sel [4:0] $end
$var wire 1 ) d_in $end
$var reg 32 . d_out [31:0] $end
$upscope $end
$scope module SEL_DEMUX $end
$var wire 1 # clock $end
$var wire 1 & load $end
$var reg 5 / count [4:0] $end
$upscope $end
$scope module TRIBUF $end
$var wire 1 % enable $end
$var wire 1 ) d_out $end
$var wire 1 " d_in $end
$upscope $end
$upscope $end
$scope module s1 $end
$var wire 1 # clock $end
$var wire 32 0 din [31:0] $end
$var wire 1 % enable $end
$var wire 1 & load $end
$var wire 1 1 rst $end
$var wire 32 2 reg_data [31:0] $end
$var wire 1 " dout $end
$var wire 1 3 d_out $end
$var wire 5 4 count [4:0] $end
$scope module DATA $end
$var wire 1 # clk $end
$var wire 32 5 din [31:0] $end
$var wire 1 & load $end
$var reg 1 1 rst $end
$var reg 32 6 temp [31:0] $end
$upscope $end
$scope module MUX16X4 $end
$var wire 32 7 d_in [31:0] $end
$var wire 1 % enable $end
$var wire 5 8 sel [4:0] $end
$var reg 1 3 d_out $end
$upscope $end
$scope module SEL_MUX $end
$var wire 1 # clock $end
$var wire 1 & load $end
$var reg 5 9 count [4:0] $end
$upscope $end
$scope module TRIBUFF $end
$var wire 1 3 din $end
$var wire 1 % enable $end
$var reg 1 " dout $end
$upscope $end
$upscope $end
$upscope $end
$enddefinitions $end
#0
$dumpvars
bx 9
bx 8
bx 7
bx 6
b10010001101000101011001111000 5
bx 4
x3
bx 2
x1
b10010001101000101011001111000 0
bx /
bx .
bx -
bx ,
bx +
bx *
z)
bx (
bx '
0&
0%
b10010001101000101011001111000 $
0#
z"
bx !
$end
#5000
11
1#
#10000
0#
#15000
1#
#19000
x)
x"
1&
1%
#20000
0#
#25000
bx0 '
bx0 +
bx0 .
0)
0"
03
b0 4
b0 8
b0 9
01
b10010001101000101011001111000 2
b10010001101000101011001111000 6
b10010001101000101011001111000 7
b0 *
b0 -
b0 /
1#
#29000
0&
#30000
0#
#35000
bx00 '
bx00 +
bx00 .
b1 *
b1 -
b1 /
11
b1 4
b1 8
b1 9
1#
#40000
0#
#45000
bx000 '
bx000 +
bx000 .
b10 4
b10 8
b10 9
b10 *
b10 -
b10 /
1#
#50000
0#
#55000
1)
1"
bx1000 '
bx1000 +
bx1000 .
13
b11 *
b11 -
b11 /
b11 4
b11 8
b11 9
1#
#60000
0#
#65000
bx11000 '
bx11000 +
bx11000 .
b100 4
b100 8
b100 9
b100 *
b100 -
b100 /
1#
#70000
0#
#75000
bx111000 '
bx111000 +
bx111000 .
b101 *
b101 -
b101 /
b101 4
b101 8
b101 9
1#
#80000
0#
#85000
bx1111000 '
bx1111000 +
bx1111000 .
b110 4
b110 8
b110 9
b110 *
b110 -
b110 /
1#
#90000
0#
#95000
0)
0"
bx01111000 '
bx01111000 +
bx01111000 .
03
b111 *
b111 -
b111 /
b111 4
b111 8
b111 9
1#
#100000
0#
#105000
bx001111000 '
bx001111000 +
bx001111000 .
b1000 4
b1000 8
b1000 9
b1000 *
b1000 -
b1000 /
1#
#110000
0#
#115000
1)
1"
bx1001111000 '
bx1001111000 +
bx1001111000 .
13
b1001 *
b1001 -
b1001 /
b1001 4
b1001 8
b1001 9
1#
#120000
0#
#125000
bx11001111000 '
bx11001111000 +
bx11001111000 .
b1010 4
b1010 8
b1010 9
b1010 *
b1010 -
b1010 /
1#
#130000
0#
#135000
0)
0"
bx011001111000 '
bx011001111000 +
bx011001111000 .
03
b1011 *
b1011 -
b1011 /
b1011 4
b1011 8
b1011 9
1#
#140000
0#
#145000
1)
1"
13
bx1011001111000 '
bx1011001111000 +
bx1011001111000 .
b1100 4
b1100 8
b1100 9
b1100 *
b1100 -
b1100 /
1#
#150000
0#
#155000
0)
0"
bx01011001111000 '
bx01011001111000 +
bx01011001111000 .
03
b1101 *
b1101 -
b1101 /
b1101 4
b1101 8
b1101 9
1#
#160000
0#
#165000
1)
1"
13
bx101011001111000 '
bx101011001111000 +
bx101011001111000 .
b1110 4
b1110 8
b1110 9
b1110 *
b1110 -
b1110 /
1#
#170000
0#
#175000
0)
0"
bx0101011001111000 '
bx0101011001111000 +
bx0101011001111000 .
03
b1111 *
b1111 -
b1111 /
b1111 4
b1111 8
b1111 9
1#
#180000
0#
#185000
bx00101011001111000 '
bx00101011001111000 +
bx00101011001111000 .
b10000 4
b10000 8
b10000 9
b10000 *
b10000 -
b10000 /
1#
#190000
0#
#195000
bx000101011001111000 '
bx000101011001111000 +
bx000101011001111000 .
b10001 *
b10001 -
b10001 /
b10001 4
b10001 8
b10001 9
1#
#200000
0#
#205000
1)
1"
13
bx1000101011001111000 '
bx1000101011001111000 +
bx1000101011001111000 .
b10010 4
b10010 8
b10010 9
b10010 *
b10010 -
b10010 /
1#
#210000
0#
#215000
0)
0"
bx01000101011001111000 '
bx01000101011001111000 +
bx01000101011001111000 .
03
b10011 *
b10011 -
b10011 /
b10011 4
b10011 8
b10011 9
1#
#220000
0#
#225000
1)
1"
13
bx101000101011001111000 '
bx101000101011001111000 +
bx101000101011001111000 .
b10100 4
b10100 8
b10100 9
b10100 *
b10100 -
b10100 /
1#
#230000
0#
#235000
bx1101000101011001111000 '
bx1101000101011001111000 +
bx1101000101011001111000 .
b10101 *
b10101 -
b10101 /
b10101 4
b10101 8
b10101 9
1#
#240000
0#
#245000
0)
0"
03
bx01101000101011001111000 '
bx01101000101011001111000 +
bx01101000101011001111000 .
b10110 4
b10110 8
b10110 9
b10110 *
b10110 -
b10110 /
1#
#250000
0#
#255000
bx001101000101011001111000 '
bx001101000101011001111000 +
bx001101000101011001111000 .
b10111 *
b10111 -
b10111 /
b10111 4
b10111 8
b10111 9
1#
#260000
0#
#265000
bx0001101000101011001111000 '
bx0001101000101011001111000 +
bx0001101000101011001111000 .
b11000 4
b11000 8
b11000 9
b11000 *
b11000 -
b11000 /
1#
#270000
0#
#275000
1)
1"
bx10001101000101011001111000 '
bx10001101000101011001111000 +
bx10001101000101011001111000 .
13
b11001 *
b11001 -
b11001 /
b11001 4
b11001 8
b11001 9
1#
#280000
0#
#285000
0)
0"
03
bx010001101000101011001111000 '
bx010001101000101011001111000 +
bx010001101000101011001111000 .
b11010 4
b11010 8
b11010 9
b11010 *
b11010 -
b11010 /
1#
#290000
0#
#295000
bx0010001101000101011001111000 '
bx0010001101000101011001111000 +
bx0010001101000101011001111000 .
b11011 *
b11011 -
b11011 /
b11011 4
b11011 8
b11011 9
1#
#300000
0#
#305000
1)
1"
13
bx10010001101000101011001111000 '
bx10010001101000101011001111000 +
bx10010001101000101011001111000 .
b11100 4
b11100 8
b11100 9
b11100 *
b11100 -
b11100 /
1#
#310000
0#
#315000
0)
0"
bx010010001101000101011001111000 '
bx010010001101000101011001111000 +
bx010010001101000101011001111000 .
03
b11101 *
b11101 -
b11101 /
b11101 4
b11101 8
b11101 9
1#
#320000
0#
#325000
bx0010010001101000101011001111000 '
bx0010010001101000101011001111000 +
bx0010010001101000101011001111000 .
b11110 4
b11110 8
b11110 9
b11110 *
b11110 -
b11110 /
1#
#330000
0#
#335000
b10010001101000101011001111000 '
b10010001101000101011001111000 +
b10010001101000101011001111000 .
b11111 *
b11111 -
b11111 /
b11111 4
b11111 8
b11111 9
1#
#340000
0#
1&
b10010000101010011010100100100 $
b10010000101010011010100100100 0
b10010000101010011010100100100 5
#345000
b0 4
b0 8
b0 9
01
b10010000101010011010100100100 2
b10010000101010011010100100100 6
b10010000101010011010100100100 7
b0 *
b0 -
b0 /
b10010001101000101011001111000 !
b10010001101000101011001111000 (
b10010001101000101011001111000 ,
1#
#350000
0#
0&
#355000
b1 *
b1 -
b1 /
11
b1 4
b1 8
b1 9
1#
#360000
0#
#365000
b10010001101000101011001111100 '
b10010001101000101011001111100 +
b10010001101000101011001111100 .
1)
1"
13
b10 4
b10 8
b10 9
b10 *
b10 -
b10 /
1#
#370000
0#
#375000
b10010001101000101011001110100 '
b10010001101000101011001110100 +
b10010001101000101011001110100 .
0)
0"
03
b11 *
b11 -
b11 /
b11 4
b11 8
b11 9
1#
#380000
0#
#385000
b10010001101000101011001100100 '
b10010001101000101011001100100 +
b10010001101000101011001100100 .
b100 4
b100 8
b100 9
b100 *
b100 -
b100 /
1#
#390000
0#
#395000
1)
1"
b10010001101000101011001100100 '
b10010001101000101011001100100 +
b10010001101000101011001100100 .
13
b101 *
b101 -
b101 /
b101 4
b101 8
b101 9
1#
#400000
0#
#405000
b10010001101000101011000100100 '
b10010001101000101011000100100 +
b10010001101000101011000100100 .
0)
0"
03
b110 4
b110 8
b110 9
b110 *
b110 -
b110 /
1#
#410000
0#
#415000
b111 *
b111 -
b111 /
b111 4
b111 8
b111 9
1#
#420000
0#
#425000
b10010001101000101011100100100 '
b10010001101000101011100100100 +
b10010001101000101011100100100 .
1)
1"
13
b1000 4
b1000 8
b1000 9
b1000 *
b1000 -
b1000 /
1#
#430000
0#
#435000
b10010001101000101010100100100 '
b10010001101000101010100100100 +
b10010001101000101010100100100 .
0)
0"
03
b1001 *
b1001 -
b1001 /
b1001 4
b1001 8
b1001 9
1#
#440000
0#
#445000
1)
1"
13
b10010001101000101010100100100 '
b10010001101000101010100100100 +
b10010001101000101010100100100 .
b1010 4
b1010 8
b1010 9
b1010 *
b1010 -
b1010 /
1#
#450000
0#
#455000
0)
0"
b10010001101000101010100100100 '
b10010001101000101010100100100 +
b10010001101000101010100100100 .
03
b1011 *
b1011 -
b1011 /
b1011 4
b1011 8
b1011 9
1#
#460000
0#
#465000
1)
1"
13
b10010001101000101010100100100 '
b10010001101000101010100100100 +
b10010001101000101010100100100 .
b1100 4
b1100 8
b1100 9
b1100 *
b1100 -
b1100 /
1#
#470000
0#
#475000
b10010001101000111010100100100 '
b10010001101000111010100100100 +
b10010001101000111010100100100 .
b1101 *
b1101 -
b1101 /
b1101 4
b1101 8
b1101 9
1#
#480000
0#
#485000
b10010001101000011010100100100 '
b10010001101000011010100100100 +
b10010001101000011010100100100 .
0)
0"
03
b1110 4
b1110 8
b1110 9
b1110 *
b1110 -
b1110 /
1#
#490000
0#
#495000
b1111 *
b1111 -
b1111 /
b1111 4
b1111 8
b1111 9
1#
#500000
0#
#505000
b10010001101010011010100100100 '
b10010001101010011010100100100 +
b10010001101010011010100100100 .
1)
1"
13
b10000 4
b10000 8
b10000 9
b10000 *
b10000 -
b10000 /
1#
#510000
0#
#515000
0)
0"
b10010001101010011010100100100 '
b10010001101010011010100100100 +
b10010001101010011010100100100 .
03
b10001 *
b10001 -
b10001 /
b10001 4
b10001 8
b10001 9
1#
#520000
0#
#525000
1)
1"
13
b10010001101010011010100100100 '
b10010001101010011010100100100 +
b10010001101010011010100100100 .
b10010 4
b10010 8
b10010 9
b10010 *
b10010 -
b10010 /
1#
#530000
0#
#535000
0)
0"
b10010001101010011010100100100 '
b10010001101010011010100100100 +
b10010001101010011010100100100 .
03
b10011 *
b10011 -
b10011 /
b10011 4
b10011 8
b10011 9
1#
#540000
0#
#545000
1)
1"
13
b10010001101010011010100100100 '
b10010001101010011010100100100 +
b10010001101010011010100100100 .
b10100 4
b10100 8
b10100 9
b10100 *
b10100 -
b10100 /
1#
#550000
0#
#555000
b10010000101010011010100100100 '
b10010000101010011010100100100 +
b10010000101010011010100100100 .
0)
0"
03
b10101 *
b10101 -
b10101 /
b10101 4
b10101 8
b10101 9
1#
#560000
0#
#565000
b10110 4
b10110 8
b10110 9
b10110 *
b10110 -
b10110 /
1#
#570000
0#
#575000
b10111 *
b10111 -
b10111 /
b10111 4
b10111 8
b10111 9
1#
#580000
0#
#585000
b11000 4
b11000 8
b11000 9
b11000 *
b11000 -
b11000 /
1#
#590000
0#
#595000
1)
1"
b10010000101010011010100100100 '
b10010000101010011010100100100 +
b10010000101010011010100100100 .
13
b11001 *
b11001 -
b11001 /
b11001 4
b11001 8
b11001 9
1#
#600000
0#
#605000
0)
0"
03
b10010000101010011010100100100 '
b10010000101010011010100100100 +
b10010000101010011010100100100 .
b11010 4
b11010 8
b11010 9
b11010 *
b11010 -
b11010 /
1#
#610000
0#
#615000
b11011 *
b11011 -
b11011 /
b11011 4
b11011 8
b11011 9
1#
#620000
0#
#625000
1)
1"
13
b10010000101010011010100100100 '
b10010000101010011010100100100 +
b10010000101010011010100100100 .
b11100 4
b11100 8
b11100 9
b11100 *
b11100 -
b11100 /
1#
#630000
0#
#635000
0)
0"
b10010000101010011010100100100 '
b10010000101010011010100100100 +
b10010000101010011010100100100 .
03
b11101 *
b11101 -
b11101 /
b11101 4
b11101 8
b11101 9
1#
#640000
0#
#645000
b11110 4
b11110 8
b11110 9
b11110 *
b11110 -
b11110 /
1#
#650000
0#
#655000
b11111 *
b11111 -
b11111 /
b11111 4
b11111 8
b11111 9
1#
#660000
0#
1&
b11000000100010010101111010000001 $
b11000000100010010101111010000001 0
b11000000100010010101111010000001 5
#665000
b10010000101010011010100100101 '
b10010000101010011010100100101 +
b10010000101010011010100100101 .
1)
1"
13
b0 4
b0 8
b0 9
01
b11000000100010010101111010000001 2
b11000000100010010101111010000001 6
b11000000100010010101111010000001 7
b0 *
b0 -
b0 /
b10010000101010011010100100100 !
b10010000101010011010100100100 (
b10010000101010011010100100100 ,
1#
#670000
0#
0&
#675000
0)
0"
b10010000101010011010100100101 '
b10010000101010011010100100101 +
b10010000101010011010100100101 .
03
b1 *
b1 -
b1 /
11
b1 4
b1 8
b1 9
1#
#680000
0#
#685000
b10010000101010011010100100001 '
b10010000101010011010100100001 +
b10010000101010011010100100001 .
b10 4
b10 8
b10 9
b10 *
b10 -
b10 /
1#
#690000
0#
#695000
b11 *
b11 -
b11 /
b11 4
b11 8
b11 9
1#
#700000
0#
#705000
b100 4
b100 8
b100 9
b100 *
b100 -
b100 /
1#
#710000
0#
#715000
b10010000101010011010100000001 '
b10010000101010011010100000001 +
b10010000101010011010100000001 .
b101 *
b101 -
b101 /
b101 4
b101 8
b101 9
1#
#720000
0#
#725000
b110 4
b110 8
b110 9
b110 *
b110 -
b110 /
1#
#730000
0#
#735000
b10010000101010011010110000001 '
b10010000101010011010110000001 +
b10010000101010011010110000001 .
1)
1"
13
b111 *
b111 -
b111 /
b111 4
b111 8
b111 9
1#
#740000
0#
#745000
b10010000101010011010010000001 '
b10010000101010011010010000001 +
b10010000101010011010010000001 .
0)
0"
03
b1000 4
b1000 8
b1000 9
b1000 *
b1000 -
b1000 /
1#
#750000
0#
#755000
b10010000101010011011010000001 '
b10010000101010011011010000001 +
b10010000101010011011010000001 .
1)
1"
13
b1001 *
b1001 -
b1001 /
b1001 4
b1001 8
b1001 9
1#
#760000
0#
#765000
b1010 4
b1010 8
b1010 9
b1010 *
b1010 -
b1010 /
1#
#770000
0#
#775000
b10010000101010011111010000001 '
b10010000101010011111010000001 +
b10010000101010011111010000001 .
b1011 *
b1011 -
b1011 /
b1011 4
b1011 8
b1011 9
1#
#780000
0#
#785000
b1100 4
b1100 8
b1100 9
b1100 *
b1100 -
b1100 /
1#
#790000
0#
#795000
b10010000101010001111010000001 '
b10010000101010001111010000001 +
b10010000101010001111010000001 .
0)
0"
03
b1101 *
b1101 -
b1101 /
b1101 4
b1101 8
b1101 9
1#
#800000
0#
#805000
b10010000101010101111010000001 '
b10010000101010101111010000001 +
b10010000101010101111010000001 .
1)
1"
13
b1110 4
b1110 8
b1110 9
b1110 *
b1110 -
b1110 /
1#
#810000
0#
#815000
0)
0"
b10010000101010101111010000001 '
b10010000101010101111010000001 +
b10010000101010101111010000001 .
03
b1111 *
b1111 -
b1111 /
b1111 4
b1111 8
b1111 9
1#
#820000
0#
#825000
1)
1"
13
b10010000101010101111010000001 '
b10010000101010101111010000001 +
b10010000101010101111010000001 .
b10000 4
b10000 8
b10000 9
b10000 *
b10000 -
b10000 /
1#
#830000
0#
#835000
0)
0"
b10010000101010101111010000001 '
b10010000101010101111010000001 +
b10010000101010101111010000001 .
03
b10001 *
b10001 -
b10001 /
b10001 4
b10001 8
b10001 9
1#
#840000
0#
#845000
b10010000100010101111010000001 '
b10010000100010101111010000001 +
b10010000100010101111010000001 .
b10010 4
b10010 8
b10010 9
b10010 *
b10010 -
b10010 /
1#
#850000
0#
#855000
b10010000110010101111010000001 '
b10010000110010101111010000001 +
b10010000110010101111010000001 .
1)
1"
13
b10011 *
b10011 -
b10011 /
b10011 4
b10011 8
b10011 9
1#
#860000
0#
#865000
b10010000010010101111010000001 '
b10010000010010101111010000001 +
b10010000010010101111010000001 .
0)
0"
03
b10100 4
b10100 8
b10100 9
b10100 *
b10100 -
b10100 /
1#
#870000
0#
#875000
b10101 *
b10101 -
b10101 /
b10101 4
b10101 8
b10101 9
1#
#880000
0#
#885000
b10110 4
b10110 8
b10110 9
b10110 *
b10110 -
b10110 /
1#
#890000
0#
#895000
b10010100010010101111010000001 '
b10010100010010101111010000001 +
b10010100010010101111010000001 .
1)
1"
13
b10111 *
b10111 -
b10111 /
b10111 4
b10111 8
b10111 9
1#
#900000
0#
#905000
0)
0"
03
b10010100010010101111010000001 '
b10010100010010101111010000001 +
b10010100010010101111010000001 .
b11000 4
b11000 8
b11000 9
b11000 *
b11000 -
b11000 /
1#
#910000
0#
#915000
b10000100010010101111010000001 '
b10000100010010101111010000001 +
b10000100010010101111010000001 .
b11001 *
b11001 -
b11001 /
b11001 4
b11001 8
b11001 9
1#
#920000
0#
#925000
b11010 4
b11010 8
b11010 9
b11010 *
b11010 -
b11010 /
1#
#930000
0#
#935000
b11011 *
b11011 -
b11011 /
b11011 4
b11011 8
b11011 9
1#
#940000
0#
#945000
b100010010101111010000001 '
b100010010101111010000001 +
b100010010101111010000001 .
b11100 4
b11100 8
b11100 9
b11100 *
b11100 -
b11100 /
1#
#950000
0#
#955000
b11101 *
b11101 -
b11101 /
b11101 4
b11101 8
b11101 9
1#
#960000
0#
#965000
b1000000100010010101111010000001 '
b1000000100010010101111010000001 +
b1000000100010010101111010000001 .
1)
1"
13
b11110 4
b11110 8
b11110 9
b11110 *
b11110 -
b11110 /
1#
#970000
0#
#975000
b11000000100010010101111010000001 '
b11000000100010010101111010000001 +
b11000000100010010101111010000001 .
b11111 *
b11111 -
b11111 /
b11111 4
b11111 8
b11111 9
1#
#980000
0#
1&
b10000100100001001101011000001001 $
b10000100100001001101011000001001 0
b10000100100001001101011000001001 5
#985000
b0 4
b0 8
b0 9
01
b10000100100001001101011000001001 2
b10000100100001001101011000001001 6
b10000100100001001101011000001001 7
b0 *
b0 -
b0 /
b11000000100010010101111010000001 !
b11000000100010010101111010000001 (
b11000000100010010101111010000001 ,
1#
#990000
0#
0&
#995000
0)
0"
b11000000100010010101111010000001 '
b11000000100010010101111010000001 +
b11000000100010010101111010000001 .
03
b1 *
b1 -
b1 /
11
b1 4
b1 8
b1 9
1#
#1000000
0#
#1005000
b10 4
b10 8
b10 9
b10 *
b10 -
b10 /
1#
#1010000
0#
#1015000
b11000000100010010101111010001001 '
b11000000100010010101111010001001 +
b11000000100010010101111010001001 .
1)
1"
13
b11 *
b11 -
b11 /
b11 4
b11 8
b11 9
1#
#1020000
0#
#1025000
0)
0"
03
b11000000100010010101111010001001 '
b11000000100010010101111010001001 +
b11000000100010010101111010001001 .
b100 4
b100 8
b100 9
b100 *
b100 -
b100 /
1#
#1030000
0#
#1035000
b101 *
b101 -
b101 /
b101 4
b101 8
b101 9
1#
#1040000
0#
#1045000
b110 4
b110 8
b110 9
b110 *
b110 -
b110 /
1#
#1050000
0#
#1055000
b11000000100010010101111000001001 '
b11000000100010010101111000001001 +
b11000000100010010101111000001001 .
b111 *
b111 -
b111 /
b111 4
b111 8
b111 9
1#
#1060000
0#
#1065000
b1000 4
b1000 8
b1000 9
b1000 *
b1000 -
b1000 /
1#
#1070000
0#
#1075000
1)
1"
b11000000100010010101111000001001 '
b11000000100010010101111000001001 +
b11000000100010010101111000001001 .
13
b1001 *
b1001 -
b1001 /
b1001 4
b1001 8
b1001 9
1#
#1080000
0#
#1085000
b1010 4
b1010 8
b1010 9
b1010 *
b1010 -
b1010 /
1#
#1090000
0#
#1095000
b11000000100010010101011000001001 '
b11000000100010010101011000001001 +
b11000000100010010101011000001001 .
0)
0"
03
b1011 *
b1011 -
b1011 /
b1011 4
b1011 8
b1011 9
1#
#1100000
0#
#1105000
1)
1"
13
b11000000100010010101011000001001 '
b11000000100010010101011000001001 +
b11000000100010010101011000001001 .
b1100 4
b1100 8
b1100 9
b1100 *
b1100 -
b1100 /
1#
#1110000
0#
#1115000
0)
0"
b11000000100010010101011000001001 '
b11000000100010010101011000001001 +
b11000000100010010101011000001001 .
03
b1101 *
b1101 -
b1101 /
b1101 4
b1101 8
b1101 9
1#
#1120000
0#
#1125000
1)
1"
13
b11000000100010010101011000001001 '
b11000000100010010101011000001001 +
b11000000100010010101011000001001 .
b1110 4
b1110 8
b1110 9
b1110 *
b1110 -
b1110 /
1#
#1130000
0#
#1135000
b11000000100010011101011000001001 '
b11000000100010011101011000001001 +
b11000000100010011101011000001001 .
b1111 *
b1111 -
b1111 /
b1111 4
b1111 8
b1111 9
1#
#1140000
0#
#1145000
b11000000100010001101011000001001 '
b11000000100010001101011000001001 +
b11000000100010001101011000001001 .
0)
0"
03
b10000 4
b10000 8
b10000 9
b10000 *
b10000 -
b10000 /
1#
#1150000
0#
#1155000
b10001 *
b10001 -
b10001 /
b10001 4
b10001 8
b10001 9
1#
#1160000
0#
#1165000
b11000000100011001101011000001001 '
b11000000100011001101011000001001 +
b11000000100011001101011000001001 .
1)
1"
13
b10010 4
b10010 8
b10010 9
b10010 *
b10010 -
b10010 /
1#
#1170000
0#
#1175000
b11000000100001001101011000001001 '
b11000000100001001101011000001001 +
b11000000100001001101011000001001 .
0)
0"
03
b10011 *
b10011 -
b10011 /
b10011 4
b10011 8
b10011 9
1#
#1180000
0#
#1185000
b10100 4
b10100 8
b10100 9
b10100 *
b10100 -
b10100 /
1#
#1190000
0#
#1195000
b10101 *
b10101 -
b10101 /
b10101 4
b10101 8
b10101 9
1#
#1200000
0#
#1205000
b10110 4
b10110 8
b10110 9
b10110 *
b10110 -
b10110 /
1#
#1210000
0#
#1215000
1)
1"
b11000000100001001101011000001001 '
b11000000100001001101011000001001 +
b11000000100001001101011000001001 .
13
b10111 *
b10111 -
b10111 /
b10111 4
b10111 8
b10111 9
1#
#1220000
0#
#1225000
0)
0"
03
b11000000100001001101011000001001 '
b11000000100001001101011000001001 +
b11000000100001001101011000001001 .
b11000 4
b11000 8
b11000 9
b11000 *
b11000 -
b11000 /
1#
#1230000
0#
#1235000
b11001 *
b11001 -
b11001 /
b11001 4
b11001 8
b11001 9
1#
#1240000
0#
#1245000
b11000100100001001101011000001001 '
b11000100100001001101011000001001 +
b11000100100001001101011000001001 .
1)
1"
13
b11010 4
b11010 8
b11010 9
b11010 *
b11010 -
b11010 /
1#
#1250000
0#
#1255000
0)
0"
b11000100100001001101011000001001 '
b11000100100001001101011000001001 +
b11000100100001001101011000001001 .
03
b11011 *
b11011 -
b11011 /
b11011 4
b11011 8
b11011 9
1#
#1260000
0#
#1265000
b11100 4
b11100 8
b11100 9
b11100 *
b11100 -
b11100 /
1#
#1270000
0#
#1275000
b11101 *
b11101 -
b11101 /
b11101 4
b11101 8
b11101 9
1#
#1280000
0#
#1285000
b10000100100001001101011000001001 '
b10000100100001001101011000001001 +
b10000100100001001101011000001001 .
b11110 4
b11110 8
b11110 9
b11110 *
b11110 -
b11110 /
1#
#1290000
0#
#1295000
1)
1"
b10000100100001001101011000001001 '
b10000100100001001101011000001001 +
b10000100100001001101011000001001 .
13
b11111 *
b11111 -
b11111 /
b11111 4
b11111 8
b11111 9
1#
#1300000
0#
1&
b10110001111100000101011001100011 $
b10110001111100000101011001100011 0
b10110001111100000101011001100011 5
#1305000
b0 4
b0 8
b0 9
01
b10110001111100000101011001100011 2
b10110001111100000101011001100011 6
b10110001111100000101011001100011 7
b0 *
b0 -
b0 /
b10000100100001001101011000001001 !
b10000100100001001101011000001001 (
b10000100100001001101011000001001 ,
1#
#1310000
0#
0&
#1315000
b10000100100001001101011000001011 '
b10000100100001001101011000001011 +
b10000100100001001101011000001011 .
b1 *
b1 -
b1 /
11
b1 4
b1 8
b1 9
1#
#1320000
0#
#1325000
0)
0"
03
b10000100100001001101011000001011 '
b10000100100001001101011000001011 +
b10000100100001001101011000001011 .
b10 4
b10 8
b10 9
b10 *
b10 -
b10 /
1#
#1330000
0#
#1335000
b10000100100001001101011000000011 '
b10000100100001001101011000000011 +
b10000100100001001101011000000011 .
b11 *
b11 -
b11 /
b11 4
b11 8
b11 9
1#
#1340000
0#
#1345000
b100 4
b100 8
b100 9
b100 *
b100 -
b100 /
1#
#1350000
0#
#1355000
b10000100100001001101011000100011 '
b10000100100001001101011000100011 +
b10000100100001001101011000100011 .
1)
1"
13
b101 *
b101 -
b101 /
b101 4
b101 8
b101 9
1#
#1360000
0#
#1365000
b10000100100001001101011001100011 '
b10000100100001001101011001100011 +
b10000100100001001101011001100011 .
b110 4
b110 8
b110 9
b110 *
b110 -
b110 /
1#
#1370000
0#
#1375000
0)
0"
b10000100100001001101011001100011 '
b10000100100001001101011001100011 +
b10000100100001001101011001100011 .
03
b111 *
b111 -
b111 /
b111 4
b111 8
b111 9
1#
#1380000
0#
#1385000
b1000 4
b1000 8
b1000 9
b1000 *
b1000 -
b1000 /
1#
#1390000
0#
#1395000
1)
1"
b10000100100001001101011001100011 '
b10000100100001001101011001100011 +
b10000100100001001101011001100011 .
13
b1001 *
b1001 -
b1001 /
b1001 4
b1001 8
b1001 9
1#
#1400000
0#
#1405000
b1010 4
b1010 8
b1010 9
b1010 *
b1010 -
b1010 /
1#
#1410000
0#
#1415000
0)
0"
b10000100100001001101011001100011 '
b10000100100001001101011001100011 +
b10000100100001001101011001100011 .
03
b1011 *
b1011 -
b1011 /
b1011 4
b1011 8
b1011 9
1#
#1420000
0#
#1425000
1)
1"
13
b10000100100001001101011001100011 '
b10000100100001001101011001100011 +
b10000100100001001101011001100011 .
b1100 4
b1100 8
b1100 9
b1100 *
b1100 -
b1100 /
1#
#1430000
0#
